cloudformation_cli_python_lib/__init__.py
cloudformation_cli_python_lib/boto3_proxy.py
cloudformation_cli_python_lib/exceptions.py
cloudformation_cli_python_lib/hook.py
cloudformation_cli_python_lib/identifier_utils.py
cloudformation_cli_python_lib/interface.py
cloudformation_cli_python_lib/log_delivery.py
cloudformation_cli_python_lib/metrics.py
cloudformation_cli_python_lib/py.typed
cloudformation_cli_python_lib/recast.py
cloudformation_cli_python_lib/resource.py
cloudformation_cli_python_lib/utils.py
cloudformation_cli_python_lib-2.1.20.dist-info/licenses/LICENSE
cloudformation_cli_python_lib-2.1.20.dist-info/METADATA
cloudformation_cli_python_lib-2.1.20.dist-info/WHEEL
cloudformation_cli_python_lib-2.1.20.dist-info/top_level.txt
cloudformation_cli_python_lib-2.1.20.dist-info/zip-safe
cloudformation_cli_python_lib-2.1.20.dist-info/RECORD
